LICENSE
MANIFEST.in
README.md
setup.py
bada_push/__init__.py
bada_push/client.py
bada_push/tests.py
python_bada_push.egg-info/PKG-INFO
python_bada_push.egg-info/SOURCES.txt
python_bada_push.egg-info/dependency_links.txt
python_bada_push.egg-info/requires.txt
python_bada_push.egg-info/top_level.txt