Metadata-Version: 1.1
Name: python-bada-push
Version: 0.3
Summary: Python module for push messaging service for Samsung Bada.
Home-page: https://bitbucket.org/godickii/python-samsung-bada-push-client
Author: Alexey Goditskiy
Author-email: godickii@gmail.com
License: BSD
Keywords: python samsung bada push messaging
Platform: any
Classifier: Development Status :: 3 - Alpha
Classifier: Intended Audience :: Developers
Classifier: License :: OSI Approved :: BSD License
Classifier: Operating System :: OS Independent
Classifier: Topic :: Software Development :: Libraries :: Python Modules
Classifier: Topic :: Communications :: Telephony
Classifier: Topic :: Internet
